slr_parser/__init__.py
slr_parser/grammar.py
slr_parser/slr_parser.py
tests/__init__.py
tests/test_grammar.py
tests/test_slr_parser.py
slr_parser-0.7.0.dist-info/LICENSE
slr_parser-0.7.0.dist-info/METADATA
slr_parser-0.7.0.dist-info/WHEEL
slr_parser-0.7.0.dist-info/entry_points.txt
slr_parser-0.7.0.dist-info/top_level.txt
slr_parser-0.7.0.dist-info/RECORD
