Metadata-Version: 2.1
Name: slr-parser
Version: 0.7.0
Summary: Implementation of Simple LR (SLR) Parser for educational purposes.
Home-page: https://github.com/Vipul97/slr-parser
Author: Vipul Gharde
Classifier: Intended Audience :: Developers
Classifier: Intended Audience :: Science/Research
Classifier: License :: OSI Approved :: MIT License
Classifier: Operating System :: MacOS
Classifier: Operating System :: Microsoft :: Windows
Classifier: Operating System :: POSIX
Classifier: Operating System :: Unix
Classifier: Programming Language :: Python
Classifier: Programming Language :: Python :: 3.12
Classifier: Topic :: Scientific/Engineering
Classifier: Topic :: Software Development
Requires-Python: >=3.12
License-File: LICENSE
Requires-Dist: graphviz
